{
    "Metadata": {
        "Name": "Vice City 3",
        "Description": "This is your Vice City dawn.",
        "Localizable": true,
        "Category": "Mesmerizing"
    },
    "InputColor": "#FFFFFF",
    "LicenseColor": "#FFFFFF",
    "ContKernelErrorColor": "#5B5A9E",
    "UncontKernelErrorColor": "#5B5A9E",
    "HostNameShellColor": "#5B5A9E",
    "UserNameShellColor": "#5B5A9E",
    "BackgroundColor": "#70365C",
    "NeutralTextColor": "#FFFFFF",
    "ListEntryColor": "#FFFFFF",
    "ListValueColor": "#5B5A9E",
    "StageColor": "#FFFFFF",
    "ErrorColor": "#5B5A9E",
    "WarningColor": "#5B5A9E",
    "OptionColor": "#5B5A9E",
    "BannerColor": "#FFFFFF",
    "NotificationTitleColor": "#FFFFFF",
    "NotificationDescriptionColor": "#FFFFFF",
    "NotificationProgressColor": "#FFFFFF",
    "NotificationFailureColor": "#5B5A9E",
    "QuestionColor": "#5B5A9E",
    "SuccessColor": "#FFFFFF",
    "UserDollarColor": "#FFFFFF",
    "TipColor": "#FFFFFF",
    "SeparatorTextColor": "#5B5A9E",
    "SeparatorColor": "#FFFFFF",
    "ListTitleColor": "#FFFFFF",
    "DevelopmentWarningColor": "#FFFFFF",
    "StageTimeColor": "#FFFFFF",
    "ProgressColor": "#FFFFFF",
    "BackOptionColor": "#5B5A9E",
    "LowPriorityBorderColor": "#FFFFFF",
    "MediumPriorityBorderColor": "#5B5A9E",
    "HighPriorityBorderColor": "#5B5A9E",
    "TableSeparatorColor": "#FFFFFF",
    "TableHeaderColor": "#5B5A9E",
    "TableValueColor": "#5B5A9E",
    "SelectedOptionColor": "#FFFFFF",
    "AlternativeOptionColor": "#5B5A9E",
    "WeekendDayColor": "#FFFFFF",
    "EventDayColor": "#FFFFFF",
    "TableTitleColor": "#FFFFFF",
    "TodayDayColor": "#FFFFFF",
    "TuiBackgroundColor": "#70365C",
    "TuiForegroundColor": "#5B5A9E",
    "TuiPaneBackgroundColor": "#70365C",
    "TuiPaneSeparatorColor": "#5B5A9E",
    "TuiPaneSelectedSeparatorColor": "#FFFFFF",
    "TuiPaneSelectedItemForeColor": "#FFFFFF",
    "TuiPaneSelectedItemBackColor": "#5B5A9E",
    "TuiPaneItemForeColor": "#5B5A9E",
    "TuiPaneItemBackColor": "#70365C",
    "TuiOptionBackgroundColor": "#5B5A9E",
    "TuiKeyBindingOptionColor": "#FFFFFF",
    "TuiOptionForegroundColor": "#FFFFFF",
    "TuiBoxBackgroundColor": "#FFFFFF",
    "TuiBoxForegroundColor": "#5B5A9E",
    "DisabledOptionColor": "#36355E",
    "TuiKeyBindingBuiltinBackgroundColor": "#5B5A9E",
    "TuiKeyBindingBuiltinColor": "#FFFFFF",
    "TuiKeyBindingBuiltinForegroundColor": "#FFFFFF"
}
