{
    "Metadata": {
        "Name": "Pastel 1",
        "Description": "Make your terminal more of a pastel terminal"
    },
    "InputColor": "204;227;222",
    "LicenseColor": "204;227;222",
    "ContKernelErrorColor": "204;147;200",
    "UncontKernelErrorColor": "191;227;125",
    "HostNameShellColor": "126;158;217",
    "UserNameShellColor": "242;240;240",
    "BackgroundColor": "0",
    "NeutralTextColor": "171;214;181",
    "ListEntryColor": "197;151;240",
    "ListValueColor": "247;236;188",
    "StageColor": "242;240;240",
    "ErrorColor": "191;227;125",
    "WarningColor": "204;147;200",
    "OptionColor": "197;151;240",
    "BannerColor": "242;240;240",
    "NotificationTitleColor": "242;240;240",
    "NotificationDescriptionColor": "171;214;181",
    "NotificationProgressColor": "197;151;240",
    "NotificationFailureColor": "191;227;125",
    "QuestionColor": "204;147;200",
    "SuccessColor": "242;240;240",
    "UserDollarColor": "171;214;181",
    "TipColor": "171;214;181",
    "SeparatorTextColor": "204;227;222",
    "SeparatorColor": "171;214;181",
    "ListTitleColor": "204;227;222",
    "DevelopmentWarningColor": "204;147;200",
    "StageTimeColor": "171;214;181",
    "ProgressColor": "197;151;240",
    "BackOptionColor": "113;199;209",
    "LowPriorityBorderColor": "204;227;222",
    "MediumPriorityBorderColor": "204;147;200",
    "HighPriorityBorderColor": "191;227;125",
    "TableSeparatorColor": "247;236;188",
    "TableHeaderColor": "204;227;222",
    "TableValueColor": "171;214;181",
    "SelectedOptionColor": "235;160;205",
    "AlternativeOptionColor": "204;147;200",
    "WeekendDayColor": "235;160;205",
    "EventDayColor": "235;160;205",
    "TableTitleColor": "235;160;205",
    "TodayDayColor": "235;160;205"
}
